README.rst
setup.cfg
setup.py
src/boogie/__init__.py
src/boogie/db.py
src/boogie/debug.py
src/boogie/decorators.py
src/boogie/functions.py
src/boogie/jinja2.py
src/boogie/render.py
src/boogie/rules.py
src/boogie/apps/__init__.py
src/boogie/apps/fragments/__init__.py
src/boogie/apps/fragments/admin.py
src/boogie/apps/fragments/apps.py
src/boogie/apps/fragments/enums.py
src/boogie/apps/fragments/functions.py
src/boogie/apps/fragments/models.py
src/boogie/apps/fragments/routes.py
src/boogie/apps/fragments/migrations/0001_initial.py
src/boogie/apps/fragments/migrations/__init__.py
src/boogie/apps/users/__init__.py
src/boogie/apps/users/admin.py
src/boogie/apps/users/apps.py
src/boogie/apps/users/models.py
src/boogie/apps/users/migrations/0001_initial.py
src/boogie/apps/users/migrations/__init__.py
src/boogie/configurations/__init__.py
src/boogie/configurations/base.py
src/boogie/configurations/descriptors.py
src/boogie/configurations/tools.py
src/boogie/configurations/apps/__init__.py
src/boogie/configurations/apps/allauth.py
src/boogie/configurations/apps/celery.py
src/boogie/configurations/apps/compressor.py
src/boogie/configurations/apps/pipeline.py
src/boogie/configurations/apps/socialauth.py
src/boogie/configurations/apps/userena.py
src/boogie/configurations/django_conf/__init__.py
src/boogie/configurations/django_conf/database.py
src/boogie/configurations/django_conf/environment.py
src/boogie/configurations/django_conf/installed_apps.py
src/boogie/configurations/django_conf/locales.py
src/boogie/configurations/django_conf/logging.py
src/boogie/configurations/django_conf/middleware.py
src/boogie/configurations/django_conf/paths.py
src/boogie/configurations/django_conf/security.py
src/boogie/configurations/django_conf/services.py
src/boogie/configurations/django_conf/templates.py
src/boogie/configurations/django_conf/urls.py
src/boogie/fields/__init__.py
src/boogie/fields/default_fields.py
src/boogie/fields/enum_field.py
src/boogie/fields/enum_type.py
src/django_boogie.egg-info/PKG-INFO
src/django_boogie.egg-info/SOURCES.txt
src/django_boogie.egg-info/dependency_links.txt
src/django_boogie.egg-info/not-zip-safe
src/django_boogie.egg-info/requires.txt
src/django_boogie.egg-info/top_level.txt