Metadata-Version: 2.1
Name: django-boogie
Version: 0.13.0
Summary: Django with swagger: better managers, APIs, configurations and url mappers.
Home-page: https://github.com/fabiommendes/django-boogie/
Author: Fábio Macêdo Mendes
Author-email: fabiomacedomendes@gmail.com
License: BSD License (BSD)
Keywords: web,django
Platform: UNKNOWN
Classifier: Development Status :: 4 - Beta
Classifier: Environment :: Web Environment
Classifier: Framework :: Django
Classifier: Intended Audience :: Developers
Classifier: License :: OSI Approved :: BSD License
Classifier: Programming Language :: Python
Classifier: Programming Language :: Python :: 3
Classifier: Programming Language :: Python :: 3.6
Classifier: Programming Language :: Python :: 3.7
Classifier: Operating System :: OS Independent
Classifier: Topic :: Internet :: WWW/HTTP
Classifier: Topic :: Internet :: WWW/HTTP :: Dynamic Content
Classifier: Topic :: Software Development :: Libraries :: Application Frameworks
Classifier: Topic :: Software Development :: Libraries :: Python Modules
Provides-Extra: dev_stack
Provides-Extra: test
Provides-Extra: extra
Provides-Extra: rest
Provides-Extra: pandas
Provides-Extra: stack
Provides-Extra: configurations
